{
    "intents": [
        {
            "intent": "GetJiraTicket"
        },
        {
            "intent": "GetInProgressJiraTickets"
        },
        {
            "intent": "GetDoneJiraTickets"
        },
        {
            "intent": "GetRemainingSprintDays"
        },
        {
            "intent": "GetRemainingStoryPoints"
        },
        {
            "intent": "AMAZON.HelpIntent"
        },
        {
            "intent": "AMAZON.StopIntent"
        },
        {
            "intent": "AMAZON.CancelIntent"
        }

    ]
}